_pistar/__init__.py
_pistar/__main__.py
_pistar/agent.py
_pistar/attachment.py
_pistar/caller.py
_pistar/collector.py
_pistar/console.py
_pistar/filesystem.py
_pistar/ide.py
_pistar/logger.py
_pistar/main.py
_pistar/node.py
_pistar/parallel.py
_pistar/report.py
_pistar/result.py
_pistar/terminal.py
_pistar/config/__init__.py
_pistar/config/cmdline.py
_pistar/config/hookspec.py
_pistar/pistar_pytest/__init__.py
_pistar/pistar_pytest/collector.py
_pistar/pistar_pytest/models.py
_pistar/pistar_pytest/plugins.py
_pistar/pistar_pytest/reporter.py
_pistar/pistar_pytest/utils.py
_pistar/utilities/__init__.py
_pistar/utilities/action_word/__init__.py
_pistar/utilities/action_word/checker.py
_pistar/utilities/action_word/decorator.py
_pistar/utilities/argument_parser/__init__.py
_pistar/utilities/argument_parser/argument_parser.py
_pistar/utilities/assertion/__init__.py
_pistar/utilities/assertion/assert_that.py
_pistar/utilities/auto_generate/__init__.py
_pistar/utilities/auto_generate/aw_code_generate_service.py
_pistar/utilities/auto_generate/generate.py
_pistar/utilities/auto_generate/generate_interface_test_service.py
_pistar/utilities/auto_generate/testcase_generate_service.py
_pistar/utilities/auto_generate/template/interface/aw.py.txt
_pistar/utilities/auto_generate/template/interface/config_util.py.txt
_pistar/utilities/auto_generate/template/interface/testcase.py.txt
_pistar/utilities/condition/__init__.py
_pistar/utilities/condition/condition.py
_pistar/utilities/constants/__init__.py
_pistar/utilities/constants/action_word.py
_pistar/utilities/constants/encode.py
_pistar/utilities/constants/file_mode.py
_pistar/utilities/constants/generate.py
_pistar/utilities/constants/pistar_logging.py
_pistar/utilities/constants/testcase.py
_pistar/utilities/constants/yaml_type.py
_pistar/utilities/exceptions/__init__.py
_pistar/utilities/exceptions/action_word.py
_pistar/utilities/exceptions/assertion.py
_pistar/utilities/exceptions/testcase.py
pistar-2.5.0.dist-info/LICENSE
pistar-2.5.0.dist-info/METADATA
pistar-2.5.0.dist-info/WHEEL
pistar-2.5.0.dist-info/entry_points.txt
pistar-2.5.0.dist-info/top_level.txt
pistar-2.5.0.dist-info/RECORD
