Metadata-Version: 2.1
Name: pistar
Version: 2.5.0
Summary: pistar: functional testing with Python
License: MIT
Keywords: test
Platform: linux
Platform: win32
Classifier: Development Status :: 6 - Mature
Classifier: Intended Audience :: Developers
Classifier: License :: OSI Approved :: MIT License
Classifier: Operating System :: Microsoft :: Windows
Classifier: Operating System :: POSIX
Classifier: Programming Language :: Python :: 3
Classifier: Programming Language :: Python :: 3 :: Only
Classifier: Programming Language :: Python :: 3.6
Classifier: Programming Language :: Python :: 3.7
Classifier: Programming Language :: Python :: 3.8
Classifier: Programming Language :: Python :: 3.9
Classifier: Topic :: Software Development :: Testing
Classifier: Topic :: Software Development :: Libraries
Requires-Python: >=3.6
License-File: LICENSE
Requires-Dist: colorama (==0.4.6)
Requires-Dist: colorlog (==6.7.0)
Requires-Dist: astunparse (==1.6.3)
Requires-Dist: Jinja2 (==3.1.2)
Requires-Dist: attrs (==22.1.0)
Requires-Dist: PyYAML (==6.0)
Requires-Dist: pytest (==7.2.2)
Requires-Dist: pluggy (==1.0.0)
Requires-Dist: dill (==0.3.4)
Requires-Dist: dnspython (==2.2.1)
Requires-Dist: eventlet (==0.33.2)
